best/__init__.py
best/integration/__init__.py
best/unit/__init__.py
best/unit/conftest.py
best/unit/test_glue_session.py
best/unit/test_glue_session_demo.py
best/unit/test_session_apis.py
vdk_poc_anonymize-19.4.6.dist-info/LICENSE.txt
vdk_poc_anonymize-19.4.6.dist-info/METADATA
vdk_poc_anonymize-19.4.6.dist-info/WHEEL
vdk_poc_anonymize-19.4.6.dist-info/top_level.txt
vdk_poc_anonymize-19.4.6.dist-info/RECORD
