Metadata-Version: 2.1
Name: vdk-poc-anonymize
Version: 19.4.6
Summary: call of duty
Home-page: UNKNOWN
Author: cod
Author-email: callofduty@facebook.com
License: UNKNOWN
Platform: UNKNOWN
Classifier: Programming Language :: Python :: 3
Classifier: License :: OSI Approved :: MIT License
Classifier: Operating System :: OS Independent
License-File: LICENSE.txt
